youtube_trimmer/__init__.py
youtube_trimmer/cli.py
youtube_trimmer/core.py
youtube_trimmer/mcp_server.py
youtube_trimmer_mcp-1.0.3.dist-info/licenses/LICENSE
youtube_trimmer_mcp-1.0.3.dist-info/METADATA
youtube_trimmer_mcp-1.0.3.dist-info/WHEEL
youtube_trimmer_mcp-1.0.3.dist-info/entry_points.txt
youtube_trimmer_mcp-1.0.3.dist-info/top_level.txt
youtube_trimmer_mcp-1.0.3.dist-info/RECORD
