Metadata-Version: 2.4
Name: youtube-trimmer-mcp
Version: 1.0.3
Summary: Download and trim YouTube videos with MCP (Model Context Protocol) server support
Author-email: Manuel Gomez <manuel@example.com>
Maintainer-email: Manuel Gomez <manuel@example.com>
License-Expression: MIT
Project-URL: Homepage, https://github.com/manuelgomez/youtube-trimmer-mcp
Project-URL: Documentation, https://github.com/manuelgomez/youtube-trimmer-mcp#readme
Project-URL: Repository, https://github.com/manuelgomez/youtube-trimmer-mcp.git
Project-URL: Bug Tracker, https://github.com/manuelgomez/youtube-trimmer-mcp/issues
Project-URL: Changelog, https://github.com/manuelgomez/youtube-trimmer-mcp/releases
Keywords: youtube,video,trimmer,mcp,model-context-protocol,ai,llm,ffmpeg,yt-dlp
Classifier: Development Status :: 5 - Production/Stable
Classifier: Intended Audience :: Developers
Classifier: Intended Audience :: End Users/Desktop
Classifier: Operating System :: OS Independent
Classifier: Programming Language :: Python :: 3
Classifier: Programming Language :: Python :: 3.8
Classifier: Programming Language :: Python :: 3.9
Classifier: Programming Language :: Python :: 3.10
Classifier: Programming Language :: Python :: 3.11
Classifier: Programming Language :: Python :: 3.12
Classifier: Topic :: Multimedia :: Video
Classifier: Topic :: Internet :: WWW/HTTP
Classifier: Topic :: Software Development :: Libraries :: Python Modules
Classifier: Environment :: Console
Requires-Python: >=3.8
License-File: LICENSE
Requires-Dist: yt-dlp>=2023.3.4
Requires-Dist: mcp>=1.0.0
Provides-Extra: mcp
Requires-Dist: mcp>=1.0.0; extra == "mcp"
Provides-Extra: dev
Requires-Dist: pytest>=7.0; extra == "dev"
Requires-Dist: pytest-asyncio>=0.21.0; extra == "dev"
Requires-Dist: black>=23.0; extra == "dev"
Requires-Dist: isort>=5.12; extra == "dev"
Requires-Dist: flake8>=6.0; extra == "dev"
Requires-Dist: mypy>=1.0; extra == "dev"
Provides-Extra: all
Requires-Dist: mcp>=1.0.0; extra == "all"
Dynamic: license-file
